[{"action":"HOLD","symbol":"R_100","price":0.0,"sl_price":"","tp_price":"","strategy":"none","timestamp":"1765318485","signature":"2320aae8d2d3ca90557939596c970bd152b2bdffc45b190f8ac831d916d6bfd9"},{"action":"SELL","symbol":"R_100","price":993.9230863490255,"sl_price":"998.8927017807706","tp_price":"983.9838554855353","strategy":"scalper","timestamp":"1765318488","signature":"35a4d55d02b0881d32515e2df1e3cd46cab1fb579d5aad312c4ae57af2844f27"},{"action":"HOLD","symbol":"R_100","price":0.0,"sl_price":"","tp_price":"","strategy":"none","timestamp":"1765318491","signature":"15ac85cde7762578a99f1b25e0bee647c0dd0fe761888c74b6e41dae02bb00d5"},{"action":"SELL","symbol":"R_100","price":994.311403914104,"sl_price":"999.2829609336744","tp_price":"984.3682898749629","strategy":"scalper","timestamp":"1765318494","signature":"5e235c49cba3d8e34f828457b13f95455e0211d30e95dd76521beb18100a4edd"},{"action":"SELL","symbol":"R_100","price":994.0233978036308,"sl_price":"998.9935147926489","tp_price":"984.0831638255945","strategy":"scalper","timestamp":"1765318497","signature":"d35511fe3bc1be213852863cc305e5cda649db6983d6f0cb8fd5ec3830350a15"},{"action":"HOLD","symbol":"R_100","price":0.0,"sl_price":"","tp_price":"","strategy":"none","timestamp":"1765318499","signature":"f26b10dbaaebfd8f098f8e790248e2005b957f913c98a66e74e6f82bfdaa0c81"},{"action":"HOLD","symbol":"R_100","price":0.0,"sl_price":"","tp_price":"","strategy":"none","timestamp":"1765318502","signature":"47855e4b80e58a90d9365629a1ce93b48202d1a399757cbc55a2b8e8e3a3c8a4"},{"action":"SELL","symbol":"R_100","price":994.2454912590631,"sl_price":"999.2167187153583","tp_price":"984.3030363464725","strategy":"scalper","timestamp":"1765318505","signature":"576ef3248027ddaf3ac7333da1826bea2f409c22047140f3f855ef6419774fe9"},{"action":"SELL","symbol":"R_100","price":994.2781977363228,"sl_price":"999.2495887250043","tp_price":"984.3354157589596","strategy":"scalper","timestamp":"1765318508","signature":"138b2b12630997219acb18475bfc1a6272db4bc0897d9f29dcd8b361e04091d8"},{"action":"SELL","symbol":"R_100","price":994.2937456442719,"sl_price":"999.2652143724931","tp_price":"984.3508081878292","strategy":"scalper","timestamp":"1765318511","signature":"6b9d87d3b90535aed3d29f4cc82b5719ea2128b313ed234b8cd92b36207fc0a1"},{"action":"SELL","symbol":"R_100","price":994.418392570776,"sl_price":"999.3904845336298","tp_price":"984.4742086450682","strategy":"scalper","timestamp":"1765318513","signature":"e979718013abcb71214e1b1705cf6a5ab4fa1cb95fe639123219ad969fd0b059"},{"action":"SELL","symbol":"R_100","price":994.6771219999033,"sl_price":"999.6505076099027","tp_price":"984.7303507799043","strategy":"scalper","timestamp":"1765318516","signature":"56f5b382455e9c0cdb7169f6306b63d0a974919c1477698b34a6eb08a4b3d829"},{"action":"SELL","symbol":"R_100","price":994.9105002860956,"sl_price":"999.885052787526","tp_price":"984.9613952832347","strategy":"scalper","timestamp":"1765318519","signature":"6c4e9f1804b2cc7b221d908c7659e183e9a4ebe6a276115fe2b91ba037866d04"},{"action":"SELL","symbol":"R_100","price":995.0549362398212,"sl_price":"1000.0302109210203","tp_price":"985.104386877423","strategy":"scalper","timestamp":"1765318522","signature":"74a4d8615dbb5069a70e63ef8e221274839bd10af5ecd8e6a9a045d42177dbe3"},{"action":"SELL","symbol":"R_100","price":995.1828294734489,"sl_price":"1000.158743620816","tp_price":"985.2310011787145","strategy":"scalper","timestamp":"1765318524","signature":"dddf4c931fc0639ddb64faef0f69984f43cf18fdd0409c03363e2bdf036964af"},{"action":"SELL","symbol":"R_100","price":995.4146744473791,"sl_price":"1000.3917478196158","tp_price":"985.4605277029053","strategy":"scalper","timestamp":"1765318527","signature":"a8f0e96a63d77d332e39256ca4c4b80f9b203934ccfdec906f848e2220ce02db"},{"action":"HOLD","symbol":"R_100","price":0.0,"sl_price":"","tp_price":"","strategy":"none","timestamp":"1765318530","signature":"e19e0d46f89d9a8a8d2509ecc070e4021b08eba19f83c5f37da8dbd323aa2397"},{"action":"HOLD","symbol":"R_100","price":0.0,"sl_price":"","tp_price":"","strategy":"none","timestamp":"1765318533","signature":"31996c25c3c72c35b843612c5e4f2a731aff09bd674595d4524e51e585ed20d1"},{"action":"HOLD","symbol":"R_100","price":0.0,"sl_price":"","tp_price":"","strategy":"none","timestamp":"1765318536","signature":"cd34df089e4a322551106b614e44c594bb9a62f043a277257a3b83e64e81fe62"},{"action":"HOLD","symbol":"R_100","price":0.0,"sl_price":"","tp_price":"","strategy":"none","timestamp":"1765318539","signature":"798783d5d8553f42770d06b30420e060e4ce39310414c4be5a39d2b5ffc24a6c"},{"action":"SELL","symbol":"R_100","price":995.78597213767,"sl_price":"1000.7649019983583","tp_price":"985.8281124162933","strategy":"scalper","timestamp":"1765318542","signature":"0fc4ca6ed177c6a700cf219ab5059c15f96304cf389e97e6d76b74377c583bef"},{"action":"HOLD","symbol":"R_100","price":0.0,"sl_price":"","tp_price":"","strategy":"none","timestamp":"1765318544","signature":"5b87287f0b9ed501b4f2fb38a52f22e7fc747275659c6f8e63023b890b533da0"},{"action":"HOLD","symbol":"R_100","price":0.0,"sl_price":"","tp_price":"","strategy":"none","timestamp":"1765318547","signature":"56d44e3b0b7b30735d0eba0da42ec2018590d2d21eaa30008a217d6cfb158565"},{"action":"HOLD","symbol":"R_100","price":0.0,"sl_price":"","tp_price":"","strategy":"none","timestamp":"1765318550","signature":"40a7326ea9be9b9cab1384d6e183f73d63e149780cf35dffb1b8e22b3b291bed"},{"action":"HOLD","symbol":"R_100","price":0.0,"sl_price":"","tp_price":"","strategy":"none","timestamp":"1765318553","signature":"3d711cc451db87e4b77236372dc081c9e6d26607ebb0d16441bf87f7ab329e6d"},{"action":"HOLD","symbol":"R_100","price":0.0,"sl_price":"","tp_price":"","strategy":"none","timestamp":"1765318555","signature":"fd74177922cf0ec397b8eb705e393f7efd2f46f89e5db4a660fa4e1554ae0dd0"},{"action":"HOLD","symbol":"R_100","price":0.0,"sl_price":"","tp_price":"","strategy":"none","timestamp":"1765318558","signature":"6bd3808bda0e5a0d0332f14fd068038963fb75aabc298400ece8eb1a291583ff"},{"action":"HOLD","symbol":"R_100","price":0.0,"sl_price":"","tp_price":"","strategy":"none","timestamp":"1765318561","signature":"011e7ae3c5c119e840355537221765ffc2fde00afc7535a271a8a1a7c604dbc9"},{"action":"HOLD","symbol":"R_100","price":0.0,"sl_price":"","tp_price":"","strategy":"none","timestamp":"1765318564","signature":"b83b719358d4c58c9514f02df22bd4b7d747eed097afae9f679f2c263ec17e1c"},{"action":"HOLD","symbol":"R_100","price":0.0,"sl_price":"","tp_price":"","strategy":"none","timestamp":"1765318566","signature":"8bfcabc0a919aea70deb6145005f3850a8b1d2170e5a7446edeea6afb8f5e0ae"},{"action":"HOLD","symbol":"R_100","price":0.0,"sl_price":"","tp_price":"","strategy":"none","timestamp":"1765318569","signature":"9dd8975ec676b249f3e72b6490292d98d114076313e4c86c32d0f52ce87eb9ae"},{"action":"HOLD","symbol":"R_100","price":0.0,"sl_price":"","tp_price":"","strategy":"none","timestamp":"1765318572","signature":"72c0e1bfc27768b534302641413d9ce21940a981df188683bd5037081f9b368c"},{"action":"HOLD","symbol":"R_100","price":0.0,"sl_price":"","tp_price":"","strategy":"none","timestamp":"1765318575","signature":"01dd14bb674c1dd6eff5716c5290ecb309a82903605e6753d72cede820ff87e9"},{"action":"HOLD","symbol":"R_100","price":0.0,"sl_price":"","tp_price":"","strategy":"none","timestamp":"1765318578","signature":"02f15fe0d407ab83e3e25f04895a3595f41e01ea44b0481f81f4f3ea61f29d9e"},{"action":"HOLD","symbol":"R_100","price":0.0,"sl_price":"","tp_price":"","strategy":"none","timestamp":"1765318581","signature":"cce4806478219b2946553433287723477da123c88735feaa4b5463ff696aa31d"},{"action":"HOLD","symbol":"R_100","price":0.0,"sl_price":"","tp_price":"","strategy":"none","timestamp":"1765318583","signature":"06400458615e650f3098f8d69bed25b7908df024420fbdea2f986e2428b46843"},{"action":"HOLD","symbol":"R_100","price":0.0,"sl_price":"","tp_price":"","strategy":"none","timestamp":"1765318586","signature":"4c6cbe37cb91a8de45b99e1eea7868fac3b520491433f8562dbd42cc28035da1"},{"action":"HOLD","symbol":"R_100","price":0.0,"sl_price":"","tp_price":"","strategy":"none","timestamp":"1765318589","signature":"9cdf4374150dda22fbaaad4624371fe481fe49361db3efb412bace107ad68276"},{"action":"HOLD","symbol":"R_100","price":0.0,"sl_price":"","tp_price":"","strategy":"none","timestamp":"1765318592","signature":"43f245bd3fc43650ed63e618ff148654c30b0c5e2a320e9d6accbff56c12b029"},{"action":"HOLD","symbol":"R_100","price":0.0,"sl_price":"","tp_price":"","strategy":"none","timestamp":"1765318595","signature":"5ff9892460e80e9d86fc10862197c4399db92f39f4d43eb82b8d7a32ee8a5cdc"},{"action":"HOLD","symbol":"R_100","price":0.0,"sl_price":"","tp_price":"","strategy":"none","timestamp":"1765318597","signature":"69528c664526127537e7d373fc6e2e1a692546f83efcd26f726587403aecf4ae"},{"action":"HOLD","symbol":"R_100","price":0.0,"sl_price":"","tp_price":"","strategy":"none","timestamp":"1765318600","signature":"877128a1988684725a1afc08a3e864c762b4ed671c8c87726ff4a10eec8bf2c5"},{"action":"HOLD","symbol":"R_100","price":0.0,"sl_price":"","tp_price":"","strategy":"none","timestamp":"1765318603","signature":"fb9dcb17755144ccce3a67ef4e642978a5b34f8a0e584af3cf93f445dc155e8f"},{"action":"HOLD","symbol":"R_100","price":0.0,"sl_price":"","tp_price":"","strategy":"none","timestamp":"1765318606","signature":"566ae9ff9515bf238842222f97f2f555aa54859f32ee2e23d871c86f2e38e449"},{"action":"HOLD","symbol":"R_100","price":0.0,"sl_price":"","tp_price":"","strategy":"none","timestamp":"1765318609","signature":"2d5a90822b0e561c8cdb16a996a2a92f8c9ba4727d17ce3770829f917e49da55"},{"action":"HOLD","symbol":"R_100","price":0.0,"sl_price":"","tp_price":"","strategy":"none","timestamp":"1765318612","signature":"a3565d000b504d34ea8dfa3f00003f163f277c04327967a43683170cd9aef341"},{"action":"HOLD","symbol":"R_100","price":0.0,"sl_price":"","tp_price":"","strategy":"none","timestamp":"1765318614","signature":"bf9b900897bd23456fa0314683a7c149bb07771d384916a71265358bcf398e5c"},{"action":"HOLD","symbol":"R_100","price":0.0,"sl_price":"","tp_price":"","strategy":"none","timestamp":"1765318617","signature":"80923852c27a1184007c39af077e43c364b71761f60920965bbf7206c1d160f2"},{"action":"HOLD","symbol":"R_100","price":0.0,"sl_price":"","tp_price":"","strategy":"none","timestamp":"1765318620","signature":"24fae603de9a7f67bf0201d1cf0dd51ab7069feb99602cc94fdcf47158562c13"},{"action":"BUY","symbol":"R_100","price":996.1722040553863,"sl_price":"991.1913430351093","tp_price":"1006.1339260959402","strategy":"scalper","timestamp":"1765318623","signature":"3e523cb55a2fa52d936531f474bdd81119f53cee304edc52d369ecb957f5cd73"}]